.bumpversion.cfg
.readthedocs.yaml
CONTRIBUTING.md
LICENSE
MANIFEST.in
Makefile
README.md
pyproject.toml
setup.py
docs/Makefile
docs/conf.py
docs/dev_intro.md
docs/index.md
docs/make.bat
docs/requirements.txt
docs/images/bullets_nopc.gif
docs/images/bullettolist_pc.gif
docs/images/bullettopar_pc.gif
docs/images/pchelp.gif
docs/images/pcnonewlines.gif
docs/images/quote_pc.gif
docs/images/quotes_nopc.gif
docs/images/remove_pc.gif
docs/images/simplequote_pc.gif
docs/images/smartcopy_pc.gif
docs/images/trimspace_nopc.gif
docs/images/trimspacing_pc.gif
prettycopy/__init__.py
prettycopy/__main__.py
prettycopy/_version.py
prettycopy/basics.py
prettycopy/command_line.py
prettycopy/prettycopy.py
prettycopy.egg-info/PKG-INFO
prettycopy.egg-info/SOURCES.txt
prettycopy.egg-info/dependency_links.txt
prettycopy.egg-info/entry_points.txt
prettycopy.egg-info/requires.txt
prettycopy.egg-info/top_level.txt
prettycopy/tests/test_all.py