Metadata-Version: 2.1
Name: prettycopy
Version: 0.2.2
Summary: A better copy-paster
Author-email: Adi Gal <adigal03@gmail.com>
License:                                  Apache License
Project-URL: repository, https://github.com/hippothebrave/prettycopy
Classifier: Development Status :: 2 - Pre-Alpha
Classifier: Programming Language :: Python :: Implementation :: CPython
Classifier: Programming Language :: Python :: Implementation :: PyPy
Classifier: Programming Language :: Python :: 3
Classifier: Programming Language :: Python :: 3.7
Classifier: Programming Language :: Python :: 3.8
Classifier: Programming Language :: Python :: 3.9
Classifier: Programming Language :: Python :: 3.10
Classifier: Programming Language :: Python :: 3.11
Requires-Python: >=3.7
Provides-Extra: develop
License-File: LICENSE
